paradigm/__init__.py
paradigm/brain.py
paradigm_brain-0.0.2.dist-info/LICENSE
paradigm_brain-0.0.2.dist-info/METADATA
paradigm_brain-0.0.2.dist-info/WHEEL
paradigm_brain-0.0.2.dist-info/top_level.txt
paradigm_brain-0.0.2.dist-info/RECORD
