Metadata-Version: 2.1
Name: paradigm-brain
Version: 0.0.2
Summary: A package provides the core implementation for various use cases of paradigm.
Home-page: https://github.com/Paradigm-shift-AI/paradigm-brain/
Author: Vedang Joshi
Author-email: vedangj044@gmail.com
License: UNKNOWN
Platform: UNKNOWN
Classifier: Programming Language :: Python :: 3.7
Classifier: License :: OSI Approved :: MIT License
